isnude/__init__.py
isnude/files/retrained_graph.pb
isnude-0.0.2.data/data/files/retrained_graph.pb/retrained_graph.pb
isnude-0.0.2.dist-info/LICENSE
isnude-0.0.2.dist-info/METADATA
isnude-0.0.2.dist-info/WHEEL
isnude-0.0.2.dist-info/entry_points.txt
isnude-0.0.2.dist-info/top_level.txt
isnude-0.0.2.dist-info/RECORD
