Metadata-Version: 2.1
Name: isnude
Version: 0.0.2
Summary: Nudity detection with re-trained Tensorflow MobileNet Model http://nudity.canaydogan.net
Home-page: https://github.com/dyaskur/nudity
Author: Dyas Yaskur
Author-email: canaydogan89@gmail.com
License: MIT
Keywords: nude,nudity,detection,pornographic,inappropriate content
Platform: UNKNOWN
Classifier: Development Status :: 4 - Beta
Classifier: License :: OSI Approved :: MIT License
Classifier: Programming Language :: Python :: 3
Requires-Python: >=3
Requires-Dist: tensorflow
